LICENSE
MANIFEST.in
README.md
setup.cfg
setup.py
django_orghierarchy/__init__.py
django_orghierarchy/admin.py
django_orghierarchy/api.py
django_orghierarchy/apps.py
django_orghierarchy/forms.py
django_orghierarchy/importers.py
django_orghierarchy/models.py
django_orghierarchy/utils.py
django_orghierarchy/management/__init__.py
django_orghierarchy/management/commands/__init__.py
django_orghierarchy/management/commands/import_organizations.py
django_orghierarchy/migrations/0001_initial.py
django_orghierarchy/migrations/0002_organization_replaced_by.py
django_orghierarchy/migrations/0003_rm_responsible_org_add_internal_type.py
django_orghierarchy/migrations/0004_add_affiliated_org_permissions.py
django_orghierarchy/migrations/0005_add_fields_to_organization_class.py
django_orghierarchy/migrations/0006_add_user_editable_to_data_source.py
django_orghierarchy/migrations/0007_set_editable_false_on_mptt_fields.py
django_orghierarchy/migrations/0008_modify_organization_on_deletes.py
django_orghierarchy/migrations/0009_add_change_organization_regular_users_permission.py
django_orghierarchy/migrations/0010_organization_private_users.py
django_orghierarchy/migrations/__init__.py
django_orghierarchy_turku.egg-info/PKG-INFO
django_orghierarchy_turku.egg-info/SOURCES.txt
django_orghierarchy_turku.egg-info/dependency_links.txt
django_orghierarchy_turku.egg-info/requires.txt
django_orghierarchy_turku.egg-info/top_level.txt
tests/__init__.py
tests/factories.py
tests/settings.py
tests/test_admin.py
tests/test_api.py
tests/test_commands.py
tests/test_forms.py
tests/test_importers.py
tests/test_models.py
tests/test_utils.py
tests/urls.py
tests/utils.py
tests/test_app/__init__.py
tests/test_app/apps.py
tests/test_app/models.py
tests/test_app/settings_custom_ds.py
tests/test_app/settings_custom_pk_ds.py
tests/test_app/migrations/0001_initial.py
tests/test_app/migrations/__init__.py
tests/test_app/tests/__init__.py
tests/test_app/tests/test_custom_data_source.py
tests/test_app/tests/test_custom_pk_data_source.py